pnq/__base/__init__.py
pnq/__base/converters.py
pnq/__base/core.py
pnq/__init__.py
pnq/__queries__.py
pnq/_itertools/__init__.py
pnq/_itertools/_async/__init__.py
pnq/_itertools/_async/concurrent.py
pnq/_itertools/_async/finalizers.py
pnq/_itertools/_async/io.py
pnq/_itertools/_async/queries.py
pnq/_itertools/_sync/__init__.py
pnq/_itertools/_sync/concurrent.py
pnq/_itertools/_sync/finalizers.py
pnq/_itertools/_sync/io.py
pnq/_itertools/_sync/queries.py
pnq/_itertools/_sync_generate/__init__.py
pnq/_itertools/_sync_generate/concurrent.py
pnq/_itertools/_sync_generate/finalizers.py
pnq/_itertools/_sync_generate/io.py
pnq/_itertools/_sync_generate/queries.py
pnq/_itertools/builder.py
pnq/_itertools/common.py
pnq/_itertools/core.py
pnq/_itertools/finalizers.py
pnq/_itertools/generate_unasync.py
pnq/_itertools/io.py
pnq/_itertools/op.py
pnq/_itertools/protocols.py
pnq/_itertools/queryables.py
pnq/_itertools/requests.py
pnq/actions.py
pnq/adapters/__init__.py
pnq/adapters/_fsspec.py
pnq/adapters/_tqdm.py
pnq/aio/__init__.py
pnq/concurrent/__init__.py
pnq/concurrent/executors.py
pnq/concurrent/iterable_functions.py
pnq/concurrent/iterables.py
pnq/concurrent/protocols.py
pnq/concurrent/testtool.py
pnq/concurrent/tools.py
pnq/ds/__init__.py
pnq/ds/ansible.py
pnq/ds/docker.py
pnq/ds/filesystem.py
pnq/ds/k8s.py
pnq/ds/logger.py
pnq/ds/multipass.py
pnq/ds/pip.py
pnq/ds/schedule.py
pnq/ds/types.py
pnq/exceptions.py
pnq/io.py
pnq/operators/__init__.py
pnq/protocols.py
pnq/queries.py
pnq/selectors/__init__.py
pnq/types/__init__.py
pnq/types/models.py
pnq/types/protocols.py
pnq/types/utils.py
pnq-0.0.21.dist-info/WHEEL
pnq-0.0.21.dist-info/METADATA
pnq-0.0.21.dist-info/RECORD
